bagga-0.0.6.dist-info/DESCRIPTION.rst
bagga-0.0.6.dist-info/METADATA
bagga-0.0.6.dist-info/RECORD
bagga-0.0.6.dist-info/WHEEL
bagga-0.0.6.dist-info/entry_points.txt
bagga-0.0.6.dist-info/metadata.json
bagga-0.0.6.dist-info/top_level.txt
docker_command_tool/__init__.py
docker_command_tool/__main__.py
docker_command_tool/build.py
docker_command_tool/cli.py
docker_command_tool/commands_docker.py
docker_command_tool/constants.py
docker_command_tool/dct.py
docker_command_tool/utils.py
tests/__init__.py
tests/test_utils.py
