Metadata-Version: 2.0
Name: bagga
Version: 0.0.6
Summary: Docker command tool
Home-page: https://github.com/kai25/docker-command-tool
Author: Vitalii Omelchenko
Author-email: vitaly.om25@gmail.com
License: UNKNOWN
Keywords: Docker,cli
Platform: UNKNOWN
Classifier: Intended Audience :: Developers
Classifier: Programming Language :: Python
Classifier: Programming Language :: Python :: 3
Classifier: Topic :: Software Development :: Libraries :: Python Modules
Requires-Dist: pyyaml (==3.11)
